toxer
