Metadata-Version: 1.0
Name: toxer
Version: 0.1.3
Summary: Run your tox tests inside docker with different linux distributions.
Home-page: UNKNOWN
Author: Aleksandr Rudakov
Author-email: ribozz@gmail.com
License: MIT
Platform: UNKNOWN
